{
  "$schema": "https://zed.dev/schema/themes/v0.2.0.json",
  "name": "NvChad Material Lighter",
  "author": "NvChad",
  "themes": [
    {
      "name": "NvChad Material Lighter",
      "appearance": "light",
      "style": {
        "accents": [
          "#6182b8",
          "#91b859",
          "#39ADB5",
          "#F59717",
          "#f76d47",
          "#7c4dff",
          "#e53935"
        ],
        "background.appearance": "opaque",
        "background": "#fafafa",
        "border": "#efefef",
        "border.disabled": "#efefef",
        "border.focused": "#B3B3B333",
        "border.selected": "#efefef",
        "border.transparent": "#efefef",
        "border.variant": "#efefef",
        "conflict": "#7c4dff",
        "conflict.background": "#fafafa",
        "conflict.border": "#C4C4C4",
        "created": "#91b859",
        "created.background": "#fafafa",
        "created.border": "#C4C4C4",
        "debugger.accent": "#e53935",
        "deleted": "#e53935",
        "deleted.background": "#fafafa",
        "deleted.border": "#C4C4C4",
        "drop_target.background": "#95a1a6",
        "editor.active_line.background": "#fafafa",
        "editor.active_line_number": "#435862",
        "editor.hover_line_number": "#6182b8",
        "editor.active_wrap_guide": "#efefef",
        "editor.background": "#fafafa",
        "editor.debugger_active_line.background": "#f76d471f",
        "editor.document_highlight.bracket_background": "#C4C4C4",
        "editor.document_highlight.read_background": "#f5f5f5",
        "editor.document_highlight.write_background": "#f5f5f5",
        "editor.foreground": "#435862",
        "editor.gutter.background": "#fafafa",
        "editor.highlighted_line.background": "#fafafa",
        "editor.indent_guide": "#f5f5f5",
        "editor.indent_guide_active": "#C4C4C4",
        "editor.invisible": null,
        "editor.line_number": "#f5f5f5",
        "editor.subheader.background": "#fafafa",
        "editor.wrap_guide": "#efefef",
        "elevated_surface.background": "#f2f2f2",
        "element.active": "#95a1a6",
        "element.background": "#fafafa",
        "element.disabled": "#D2D4D5",
        "element.hover": "#C4C4C4",
        "element.selected": "#C4C4C4",
        "error": "#e53935",
        "error.background": "#fafafa",
        "error.border": "#C4C4C4",
        "ghost_element.active": "#95a1a6",
        "ghost_element.background": "#fafafa",
        "ghost_element.disabled": "#D2D4D5",
        "ghost_element.hover": "#C4C4C4",
        "ghost_element.selected": "#C4C4C4",
        "hidden": "#839197",
        "hidden.background": "#fafafa",
        "hidden.border": "#C4C4C4",
        "hint": "#C4C4C4",
        "hint.background": "#fafafa",
        "hint.border": "#C4C4C4",
        "icon": "#C4C4C4",
        "icon.accent": "#39ADB5",
        "icon.disabled": "#D2D4D5",
        "icon.muted": "#C4C4C4",
        "icon.placeholder": "#C4C4C4",
        "ignored": "#a8b1b6",
        "ignored.background": "#fafafa",
        "ignored.border": "#C4C4C4",
        "info": "#91b859",
        "info.background": "#fafafa",
        "info.border": "#C4C4C4",
        "link_text.hover": "#39ADB5",
        "minimap.thumb.active_background": "#6182b873",
        "minimap.thumb.background": "#6182b833",
        "minimap.thumb.border": null,
        "minimap.thumb.hover_background": "#6182b84d",
        "modified": "#F59717",
        "modified.background": "#fafafa",
        "modified.border": "#C4C4C4",
        "pane.focused_border": null,
        "pane_group.border": "#efefef",
        "panel.background": "#EEEEEE",
        "panel.focused_border": null,
        "panel.indent_guide": "#f5f5f5",
        "panel.indent_guide_active": "#C4C4C4",
        "panel.indent_guide_hover": "#C4C4C4",
        "panel.overlay_background": "#f2f2f2",
        "panel.overlay_hover": "#C4C4C4",
        "players": [
          {
            "background": "#6182b8",
            "cursor": "#6182b8",
            "selection": "#6182b84d"
          },
          {
            "background": "#91b859",
            "cursor": "#91b859",
            "selection": "#91b8594d"
          },
          {
            "background": "#39ADB5",
            "cursor": "#39ADB5",
            "selection": "#39ADB54d"
          },
          {
            "background": "#F59717",
            "cursor": "#F59717",
            "selection": "#F597174d"
          },
          {
            "background": "#f76d47",
            "cursor": "#f76d47",
            "selection": "#f76d474d"
          },
          {
            "background": "#7c4dff",
            "cursor": "#7c4dff",
            "selection": "#7c4dff4d"
          },
          {
            "background": "#e53935",
            "cursor": "#e53935",
            "selection": "#e539354d"
          }
        ],
        "predictive": "#C4C4C4",
        "predictive.background": "#C4C4C41a",
        "predictive.border": "#C4C4C4",
        "renamed": "#39ADB5",
        "renamed.background": "#fafafa",
        "renamed.border": "#C4C4C4",
        "scrollbar.thumb.background": "#C4C4C480",
        "scrollbar.thumb.hover_background": "#C4C4C4",
        "scrollbar.thumb.border": "#C4C4C4",
        "scrollbar.track.background": "#fafafa80",
        "scrollbar.track.border": "#efefef",
        "search.active_match_background": "#C4C4C4",
        "search.match_background": "#C4C4C4",
        "status_bar.background": "#EEEEEE",
        "success": "#91b859",
        "success.background": "#fafafa",
        "success.border": "#C4C4C4",
        "surface.background": "#EEEEEE",
        "syntax": {
          "attribute": {
            "color": "#00BCD4",
            "font_style": null,
            "font_weight": null
          },
          "boolean": {
            "color": "#F76D47",
            "font_style": null,
            "font_weight": null
          },
          "character": {
            "color": "#F59717",
            "font_style": null,
            "font_weight": null
          },
          "character.special": {
            "color": "#7C4DFF",
            "font_style": null,
            "font_weight": null
          },
          "concept": {
            "color": "#7C4DFF",
            "font_style": null,
            "font_weight": null
          },
          "constant": {
            "color": "#F76D47",
            "font_style": null,
            "font_weight": null
          },
          "constant.builtin": {
            "color": "#F76D47",
            "font_style": null,
            "font_weight": null
          },
          "constant.macro": {
            "color": "#7C4DFF",
            "font_style": null,
            "font_weight": null
          },
          "comment.documentation": {
            "color": "#C4C4C4",
            "font_style": null,
            "font_weight": null
          },
          "emphasis": {
            "color": "#F76D47",
            "font_style": null,
            "font_weight": 700
          },
          "emphasis.strong": {
            "color": "#F59717",
            "font_style": null,
            "font_weight": 700
          },
          "enum": {
            "color": "#00BCD4",
            "font_style": null,
            "font_weight": null
          },
          "label": {
            "color": "#435862",
            "font_style": null,
            "font_weight": null
          },
          "number": {
            "color": "#F76D47",
            "font_style": null,
            "font_weight": null
          },
          "number.float": {
            "color": "#F76D47",
            "font_style": null,
            "font_weight": null
          },
          "operator": {
            "color": "#39adb5",
            "font_style": null,
            "font_weight": null
          },
          "punctuation": {
            "color": "#D2D4D5",
            "font_style": null,
            "font_weight": null
          },
          "punctuation.bracket": {
            "color": "#39adb5",
            "font_style": null,
            "font_weight": null
          },
          "punctuation.delimiter": {
            "color": "#39adb5",
            "font_style": null,
            "font_weight": null
          },
          "punctuation.list_marker": {
            "color": "#D2D4D5",
            "font_style": null,
            "font_weight": null
          },
          "punctuation.special": {
            "color": "#39ADB5",
            "font_style": null,
            "font_weight": null
          },
          "preproc": {
            "color": "#39ADB5",
            "font_style": null,
            "font_weight": null
          },
          "property": {
            "color": "#F59717",
            "font_style": null,
            "font_weight": null
          },
          "property.json": {
            "color": "#F59717",
            "font_style": null,
            "font_weight": null
          },
          "string": {
            "color": "#91B859",
            "font_style": null,
            "font_weight": null
          },
          "string.documentation": {
            "color": "#C4C4C4",
            "font_style": null,
            "font_weight": null
          },
          "string.escape": {
            "color": "#39ADB5",
            "font_style": null,
            "font_weight": null
          },
          "string.regex": {
            "color": "#39ADB5",
            "font_style": null,
            "font_weight": null
          },
          "string.special": {
            "color": "#91B859",
            "font_style": null,
            "font_weight": null
          },
          "string.special.symbol": {
            "color": "#91B859",
            "font_style": null,
            "font_weight": null
          },
          "string.special.url": {
            "color": "#39ADB5",
            "font_style": "italic",
            "font_weight": null
          },
          "tag": {
            "color": "#00BCD4",
            "font_style": null,
            "font_weight": null
          },
          "tag.doctype": {
            "color": "#F59717",
            "font_style": null,
            "font_weight": null
          },
          "text.literal": {
            "color": "#435862",
            "font_style": null,
            "font_weight": null
          },
          "title": {
            "color": "#6182B8",
            "font_style": null,
            "font_weight": 700
          },
          "type": {
            "color": "#00BCD4",
            "font_style": null,
            "font_weight": null
          },
          "type.builtin": {
            "color": "#7c4dff",
            "font_style": null,
            "font_weight": null
          },
          "type.definition": {
            "color": "#00BCD4",
            "font_style": null,
            "font_weight": null
          },
          "type.interface": {
            "color": "#00BCD4",
            "font_style": null,
            "font_weight": null
          },
          "type.super": {
            "color": "#00BCD4",
            "font_style": null,
            "font_weight": null
          },
          "variable": {
            "color": "#546e7a",
            "font_style": null,
            "font_weight": null
          },
          "variable.builtin": {
            "color": "#F76D47",
            "font_style": null,
            "font_weight": null
          },
          "variable.member": {
            "color": "#546e7a",
            "font_style": null,
            "font_weight": null
          },
          "variable.parameter": {
            "color": "#f76d47",
            "font_style": null,
            "font_weight": null
          },
          "variable.special": {
            "color": "#F59717",
            "font_style": null,
            "font_weight": null
          },
          "hint": {
            "color": "#C4C4C4",
            "font_style": "italic",
            "font_weight": null
          },
          "link_text": {
            "color": "#F59717",
            "font_style": null,
            "font_weight": null
          },
          "link_uri": {
            "color": "#F76D47",
            "font_style": null,
            "font_weight": null
          },
          "embedded": {
            "color": "#435862",
            "font_style": null,
            "font_weight": null
          },
          "variant": {
            "color": "#39ADB5",
            "font_style": null,
            "font_weight": null
          },
          "primary": {
            "color": "#6182b8",
            "font_style": null,
            "font_weight": null
          },
          "keyword.control": {
            "color": "#7C4DFF",
            "font_style": null,
            "font_weight": null
          },
          "function": {
            "color": "#6182b8",
            "font_style": null,
            "font_weight": null
          },
          "function.builtin": {
            "color": "#6182B8",
            "font_style": null,
            "font_weight": null
          },
          "function.call": {
            "color": "#6182b8",
            "font_style": null,
            "font_weight": null
          },
          "function.method": {
            "color": "#6182b8",
            "font_style": null,
            "font_weight": null
          },
          "function.method.call": {
            "color": "#6182B8",
            "font_style": null,
            "font_weight": null
          },
          "function.macro": {
            "color": "#FF5370",
            "font_style": null,
            "font_weight": null
          },
          "constructor": {
            "color": "#39ADB5",
            "font_style": null,
            "font_weight": null
          },
          "keyword": {
            "color": "#7C4DFF",
            "font_style": null,
            "font_weight": null
          },
          "comment": {
            "color": "#C4C4C4",
            "font_style": "italic",
            "font_weight": null
          },
          "comment.doc": {
            "color": "#BDBDBD",
            "font_style": "italic",
            "font_weight": null
          },
          "module": {
            "color": "#546e7a",
            "font_style": null,
            "font_weight": null
          },
          "keyword.exception": {
            "color": "#F59717",
            "font_style": null,
            "font_weight": null
          },
          "keyword.function": {
            "color": "#7C4DFF",
            "font_style": null,
            "font_weight": null
          },
          "keyword.return": {
            "color": "#7C4DFF",
            "font_style": null,
            "font_weight": null
          },
          "keyword.operator": {
            "color": "#7C4DFF",
            "font_style": null,
            "font_weight": null
          },
          "keyword.import": {
            "color": "#7C4DFF",
            "font_style": null,
            "font_weight": null
          },
          "keyword.conditional": {
            "color": "#7C4DFF",
            "font_style": null,
            "font_weight": null
          },
          "keyword.repeat": {
            "color": "#00BCD4",
            "font_style": null,
            "font_weight": null
          },
          "keyword.directive": {
            "color": "#00BCD4",
            "font_style": null,
            "font_weight": null
          },
          "tag.attribute": {
            "color": "#F59717",
            "font_style": null,
            "font_weight": null
          },
          "tag.delimiter": {
            "color": "#fafafa",
            "font_style": null,
            "font_weight": null
          },
          "Number": {
            "color": "#F76D47",
            "font_style": null,
            "font_weight": null
          },
          "StorageClass": {
            "color": "#7c4dff",
            "font_style": null,
            "font_weight": null
          },
          "Repeat": {
            "color": "#7c4dff",
            "font_style": null,
            "font_weight": null
          },
          "Define": {
            "color": "#6182b8",
            "font_style": null,
            "font_weight": null
          }
        },
        "tab.active_background": "#C4C4C4",
        "tab.active_border_top": "#6182b8",
        "tab.hover_background": "#C4C4C4",
        "tab.inactive_background": "#EEEEEE",
        "tab_bar.background": "#EEEEEE",
        "terminal.ansi.background": "#EEEEEE",
        "terminal.ansi.black": "#EBEBEB",
        "terminal.ansi.blue": "#6182b8",
        "terminal.ansi.bright_black": "#C4C4C4",
        "terminal.ansi.bright_blue": "#6182B8",
        "terminal.ansi.bright_cyan": "#39ADB5",
        "terminal.ansi.bright_green": "#a7c67a",
        "terminal.ansi.bright_magenta": "#9671ff",
        "terminal.ansi.bright_red": "#FF5370",
        "terminal.ansi.bright_white": "#546e7a",
        "terminal.ansi.bright_yellow": "#f6a434",
        "terminal.ansi.cyan": "#39adb5",
        "terminal.ansi.dim_black": "#EBEBEB",
        "terminal.ansi.dim_blue": "#4e73ae",
        "terminal.ansi.dim_cyan": "#39adb5",
        "terminal.ansi.dim_green": "#91b859",
        "terminal.ansi.dim_magenta": "#7c4dff",
        "terminal.ansi.dim_red": "#e53935",
        "terminal.ansi.dim_white": "#B3B3B3",
        "terminal.ansi.dim_yellow": "#F59717",
        "terminal.ansi.green": "#91b859",
        "terminal.ansi.magenta": "#7c4dff",
        "terminal.ansi.red": "#e53935",
        "terminal.ansi.white": "#C4C4C4",
        "terminal.ansi.yellow": "#F59717",
        "terminal.background": "#EEEEEE",
        "terminal.bright_foreground": "#546e7a",
        "terminal.dim_foreground": "#C4C4C4",
        "terminal.foreground": "#435862",
        "text": "#435862",
        "text.accent": "#39ADB5",
        "text.disabled": "#D2D4D5",
        "text.muted": "#C4C4C4",
        "text.placeholder": "#C4C4C4",
        "title_bar.background": "#EEEEEE",
        "title_bar.inactive_background": "#EEEEEE",
        "toolbar.background": "#EEEEEE",
        "toolbar.hover_background": "#C4C4C4",
        "unreachable": "#e53935",
        "unreachable.background": "#fafafa",
        "unreachable.border": "#C4C4C4",
        "version_control.added": "#91b859",
        "version_control.added_background": "#fafafa",
        "version_control.conflict": "#7c4dff",
        "version_control.conflict_background": "#fafafa",
        "version_control.conflict_marker.ours": "#91b85933",
        "version_control.conflict_marker.theirs": "#F5971733",
        "version_control.deleted": "#e53935",
        "version_control.deleted_background": "#fafafa",
        "version_control.ignored": "#839197",
        "version_control.modified": "#F59717",
        "version_control.modified_background": "#fafafa",
        "version_control.renamed": "#39ADB5",
        "version_control.word_added": "#91b85959",
        "version_control.word_deleted": "#e53935cc",
        "vim.helix_normal.background": "#6182b8",
        "vim.helix_normal.foreground": "#fafafa",
        "vim.helix_select.background": "#39ADB5",
        "vim.helix_select.foreground": "#fafafa",
        "vim.insert.background": "#91b859",
        "vim.insert.foreground": "#fafafa",
        "vim.mode.text": "#435862",
        "vim.normal.background": "#6182b8",
        "vim.normal.foreground": "#fafafa",
        "vim.replace.background": "#e53935",
        "vim.replace.foreground": "#fafafa",
        "vim.visual.background": "#7c4dff",
        "vim.visual.foreground": "#fafafa",
        "vim.visual_block.background": "#f76d47",
        "vim.visual_block.foreground": "#fafafa",
        "vim.visual_line.background": "#F59717",
        "vim.visual_line.foreground": "#fafafa",
        "warning": "#F59717",
        "warning.background": "#fafafa",
        "warning.border": "#C4C4C4"
      }
    }
  ]
}
