{
  "$schema": "https://zed.dev/schema/themes/v0.2.0.json",
  "name": "NvChad Tomorrow Night",
  "author": "NvChad",
  "themes": [
    {
      "name": "NvChad Tomorrow Night",
      "appearance": "dark",
      "style": {
        "accents": [
          "#6f8dab",
          "#a4b595",
          "#8abdb6",
          "#d7bd8d",
          "#DE935F",
          "#b4bbc8",
          "#cc6666"
        ],
        "background.appearance": "opaque",
        "background": "#1d1f21",
        "border": "#121315",
        "border.disabled": "#121315",
        "border.focused": "#676e7b33",
        "border.selected": "#121315",
        "border.transparent": "#121315",
        "border.variant": "#121315",
        "conflict": "#DE935F",
        "conflict.background": "#1d1f21",
        "conflict.border": "#353b45",
        "created": "#a4b595",
        "created.background": "#1d1f21",
        "created.border": "#353b45",
        "debugger.accent": "#cc6666",
        "deleted": "#cc6666",
        "deleted.background": "#1d1f21",
        "deleted.border": "#353b45",
        "drop_target.background": "#30343c",
        "editor.active_line.background": "#232527",
        "editor.active_line_number": "#c5c8c6",
        "editor.hover_line_number": "#6f8dab",
        "editor.active_wrap_guide": "#121315",
        "editor.background": "#1d1f21",
        "editor.debugger_active_line.background": "#DE935F1f",
        "editor.document_highlight.bracket_background": "#353b45",
        "editor.document_highlight.read_background": "#2a2e35",
        "editor.document_highlight.write_background": "#2a2e35",
        "editor.foreground": "#c5c8c6",
        "editor.gutter.background": "#1d1f21",
        "editor.highlighted_line.background": "#232527",
        "editor.indent_guide": "#1b1d1f",
        "editor.indent_guide_active": "#545B68",
        "editor.invisible": null,
        "editor.line_number": "#1b1d1f",
        "editor.subheader.background": "#1d1f21",
        "editor.wrap_guide": "#121315",
        "elevated_surface.background": "#17181a",
        "element.active": "#30343c",
        "element.background": "#1d1f21",
        "element.disabled": "#616875",
        "element.hover": "#545B68",
        "element.selected": "#545B68",
        "error": "#cc6666",
        "error.background": "#1d1f21",
        "error.border": "#353b45",
        "ghost_element.active": "#30343c",
        "ghost_element.background": "#1d1f21",
        "ghost_element.disabled": "#616875",
        "ghost_element.hover": "#545B68",
        "ghost_element.selected": "#545B68",
        "hidden": "#b4b7b4",
        "hidden.background": "#1d1f21",
        "hidden.border": "#353b45",
        "hint": "#b4bbc8",
        "hint.background": "#1d1f21",
        "hint.border": "#353b45",
        "icon": "#b4b7b4",
        "icon.accent": "#8abdb6",
        "icon.disabled": "#616875",
        "icon.muted": "#b4b7b4",
        "icon.placeholder": "#545B68",
        "ignored": "#b4b7b4",
        "ignored.background": "#1d1f21",
        "ignored.border": "#353b45",
        "info": "#a4b595",
        "info.background": "#1d1f21",
        "info.border": "#353b45",
        "link_text.hover": "#8abdb6",
        "minimap.thumb.active_background": "#6f8dab73",
        "minimap.thumb.background": "#6f8dab33",
        "minimap.thumb.border": null,
        "minimap.thumb.hover_background": "#6f8dab4d",
        "modified": "#d7bd8d",
        "modified.background": "#1d1f21",
        "modified.border": "#353b45",
        "pane.focused_border": null,
        "pane_group.border": "#121315",
        "panel.background": "#191b1d",
        "panel.focused_border": null,
        "panel.indent_guide": "#1b1d1f",
        "panel.indent_guide_active": "#545B68",
        "panel.indent_guide_hover": "#545B68",
        "panel.overlay_background": "#17181a",
        "players": [
          {
            "background": "#6f8dab",
            "cursor": "#6f8dab",
            "selection": "#6f8dab4d"
          },
          {
            "background": "#a4b595",
            "cursor": "#a4b595",
            "selection": "#a4b5954d"
          },
          {
            "background": "#8abdb6",
            "cursor": "#8abdb6",
            "selection": "#8abdb64d"
          },
          {
            "background": "#d7bd8d",
            "cursor": "#d7bd8d",
            "selection": "#d7bd8d4d"
          },
          {
            "background": "#DE935F",
            "cursor": "#DE935F",
            "selection": "#DE935F4d"
          },
          {
            "background": "#b4bbc8",
            "cursor": "#b4bbc8",
            "selection": "#b4bbc84d"
          },
          {
            "background": "#cc6666",
            "cursor": "#cc6666",
            "selection": "#cc66664d"
          }
        ],
        "predictive": "#b4b7b4",
        "predictive.background": "#1d1f21",
        "predictive.border": "#353b45",
        "renamed": "#8abdb6",
        "renamed.background": "#1d1f21",
        "renamed.border": "#353b45",
        "scrollbar.thumb.background": "#353b4580",
        "scrollbar.thumb.hover_background": "#353b45",
        "scrollbar.thumb.border": "#353b45",
        "scrollbar.track.background": "#1d1f2180",
        "scrollbar.track.border": "#121315",
        "search.active_match_background": "#353b45",
        "search.match_background": "#353b45",
        "status_bar.background": "#191b1d",
        "success": "#a4b595",
        "success.background": "#1d1f21",
        "success.border": "#353b45",
        "surface.background": "#191b1d",
        "syntax": {
          "attribute": {
            "color": "#f0c674",
            "font_style": null,
            "font_weight": null
          },
          "boolean": {
            "color": "#de935f",
            "font_style": null,
            "font_weight": null
          },
          "character": {
            "color": "#cc6666",
            "font_style": null,
            "font_weight": null
          },
          "character.special": {
            "color": "#b294bb",
            "font_style": null,
            "font_weight": null
          },
          "concept": {
            "color": "#b294bb",
            "font_style": null,
            "font_weight": null
          },
          "constant": {
            "color": "#de935f",
            "font_style": null,
            "font_weight": null
          },
          "constant.builtin": {
            "color": "#de935f",
            "font_style": null,
            "font_weight": null
          },
          "constant.macro": {
            "color": "#b294bb",
            "font_style": null,
            "font_weight": null
          },
          "comment.documentation": {
            "color": "#b4b7b4",
            "font_style": null,
            "font_weight": null
          },
          "emphasis": {
            "color": "#de935f",
            "font_style": null,
            "font_weight": 700
          },
          "emphasis.strong": {
            "color": "#cc6666",
            "font_style": null,
            "font_weight": 700
          },
          "enum": {
            "color": "#f0c674",
            "font_style": null,
            "font_weight": null
          },
          "label": {
            "color": "#c5c8c6",
            "font_style": null,
            "font_weight": null
          },
          "number": {
            "color": "#de935f",
            "font_style": null,
            "font_weight": null
          },
          "number.float": {
            "color": "#de935f",
            "font_style": null,
            "font_weight": null
          },
          "operator": {
            "color": "#c5c8c6",
            "font_style": null,
            "font_weight": null
          },
          "punctuation": {
            "color": "#70c0b1",
            "font_style": null,
            "font_weight": null
          },
          "punctuation.bracket": {
            "color": "#a4b595",
            "font_style": null,
            "font_weight": null
          },
          "punctuation.delimiter": {
            "color": "#C5C8C2",
            "font_style": null,
            "font_weight": null
          },
          "punctuation.list_marker": {
            "color": "#70c0b1",
            "font_style": null,
            "font_weight": null
          },
          "punctuation.special": {
            "color": "#70c0b1",
            "font_style": null,
            "font_weight": null
          },
          "preproc": {
            "color": "#8abeb7",
            "font_style": null,
            "font_weight": null
          },
          "property": {
            "color": "#cc6666",
            "font_style": null,
            "font_weight": null
          },
          "property.json": {
            "color": "#cc6666",
            "font_style": null,
            "font_weight": null
          },
          "string": {
            "color": "#b5bd68",
            "font_style": null,
            "font_weight": null
          },
          "string.documentation": {
            "color": "#b4b7b4",
            "font_style": null,
            "font_weight": null
          },
          "string.escape": {
            "color": "#8abeb7",
            "font_style": null,
            "font_weight": null
          },
          "string.regex": {
            "color": "#8abeb7",
            "font_style": null,
            "font_weight": null
          },
          "string.special": {
            "color": "#b5bd68",
            "font_style": null,
            "font_weight": null
          },
          "string.special.symbol": {
            "color": "#b5bd68",
            "font_style": null,
            "font_weight": null
          },
          "string.special.url": {
            "color": "#8abdb6",
            "font_style": "italic",
            "font_weight": null
          },
          "tag": {
            "color": "#f0c674",
            "font_style": null,
            "font_weight": null
          },
          "tag.doctype": {
            "color": "#cc6666",
            "font_style": null,
            "font_weight": null
          },
          "text.literal": {
            "color": "#c5c8c6",
            "font_style": null,
            "font_weight": null
          },
          "title": {
            "color": "#81a2be",
            "font_style": null,
            "font_weight": 700
          },
          "type": {
            "color": "#f0c674",
            "font_style": null,
            "font_weight": null
          },
          "type.builtin": {
            "color": "#f0c674",
            "font_style": null,
            "font_weight": null
          },
          "type.definition": {
            "color": "#f0c674",
            "font_style": null,
            "font_weight": null
          },
          "type.interface": {
            "color": "#f0c674",
            "font_style": null,
            "font_weight": null
          },
          "type.super": {
            "color": "#f0c674",
            "font_style": null,
            "font_weight": null
          },
          "variable": {
            "color": "#c5c8c6",
            "font_style": null,
            "font_weight": null
          },
          "variable.builtin": {
            "color": "#de935f",
            "font_style": null,
            "font_weight": null
          },
          "variable.member": {
            "color": "#cc6666",
            "font_style": null,
            "font_weight": null
          },
          "variable.parameter": {
            "color": "#cc6666",
            "font_style": null,
            "font_weight": null
          },
          "variable.special": {
            "color": "#cc6666",
            "font_style": null,
            "font_weight": null
          },
          "hint": {
            "color": "#b4b7b4",
            "font_style": "italic",
            "font_weight": null
          },
          "link_text": {
            "color": "#cc6666",
            "font_style": null,
            "font_weight": null
          },
          "link_uri": {
            "color": "#de935f",
            "font_style": null,
            "font_weight": null
          },
          "embedded": {
            "color": "#c5c8c6",
            "font_style": null,
            "font_weight": null
          },
          "variant": {
            "color": "#8abeb7",
            "font_style": null,
            "font_weight": null
          },
          "primary": {
            "color": "#6f8dab",
            "font_style": null,
            "font_weight": null
          },
          "keyword.control": {
            "color": "#b294bb",
            "font_style": null,
            "font_weight": null
          },
          "function": {
            "color": "#6f8dab",
            "font_style": null,
            "font_weight": null
          },
          "function.builtin": {
            "color": "#d7bd8d",
            "font_style": null,
            "font_weight": null
          },
          "function.call": {
            "color": "#6f8dab",
            "font_style": null,
            "font_weight": null
          },
          "function.method": {
            "color": "#6f8dab",
            "font_style": null,
            "font_weight": null
          },
          "function.method.call": {
            "color": "#81a2be",
            "font_style": null,
            "font_weight": null
          },
          "function.macro": {
            "color": "#cc6666",
            "font_style": null,
            "font_weight": null
          },
          "constructor": {
            "color": "#8abeb7",
            "font_style": null,
            "font_weight": null
          },
          "keyword": {
            "color": "#b294bb",
            "font_style": null,
            "font_weight": null
          },
          "comment": {
            "color": "#545B68",
            "font_style": "italic",
            "font_weight": null
          },
          "comment.doc": {
            "color": "#616875",
            "font_style": "italic",
            "font_weight": null
          },
          "module": {
            "color": "#cc6666",
            "font_style": null,
            "font_weight": null
          },
          "keyword.exception": {
            "color": "#cc6666",
            "font_style": null,
            "font_weight": null
          },
          "keyword.function": {
            "color": "#b294bb",
            "font_style": null,
            "font_weight": null
          },
          "keyword.return": {
            "color": "#b294bb",
            "font_style": null,
            "font_weight": null
          },
          "keyword.operator": {
            "color": "#b294bb",
            "font_style": null,
            "font_weight": null
          },
          "keyword.import": {
            "color": "#b294bb",
            "font_style": null,
            "font_weight": null
          },
          "keyword.conditional": {
            "color": "#b294bb",
            "font_style": null,
            "font_weight": null
          },
          "keyword.repeat": {
            "color": "#f0c674",
            "font_style": null,
            "font_weight": null
          },
          "keyword.directive": {
            "color": "#f0c674",
            "font_style": null,
            "font_weight": null
          },
          "tag.attribute": {
            "color": "#cc6666",
            "font_style": null,
            "font_weight": null
          },
          "tag.delimiter": {
            "color": "#a4b595",
            "font_style": null,
            "font_weight": null
          },
          "Number": {
            "color": "#de935f",
            "font_style": null,
            "font_weight": null
          }
        },
        "tab.active_background": "#353b45",
        "tab.active_border_top": "#6f8dab",
        "tab.hover_background": "#545B68",
        "tab.inactive_background": "#191b1d",
        "tab_bar.background": "#191b1d",
        "terminal.ansi.background": "#191b1d",
        "terminal.ansi.black": "#232527",
        "terminal.ansi.blue": "#6f8dab",
        "terminal.ansi.bright_black": "#545B68",
        "terminal.ansi.bright_blue": "#81a2be",
        "terminal.ansi.bright_cyan": "#8abdb6",
        "terminal.ansi.bright_green": "#a3b991",
        "terminal.ansi.bright_magenta": "#b290ac",
        "terminal.ansi.bright_red": "#FF6E79",
        "terminal.ansi.bright_white": "#ffffff",
        "terminal.ansi.bright_yellow": "#e4c180",
        "terminal.ansi.cyan": "#70c0b1",
        "terminal.ansi.dim_black": "#232527",
        "terminal.ansi.dim_blue": "#728da8",
        "terminal.ansi.dim_cyan": "#70c0b1",
        "terminal.ansi.dim_green": "#a4b595",
        "terminal.ansi.dim_magenta": "#b4bbc8",
        "terminal.ansi.dim_red": "#cc6666",
        "terminal.ansi.dim_white": "#676e7b",
        "terminal.ansi.dim_yellow": "#d7bd8d",
        "terminal.ansi.green": "#a4b595",
        "terminal.ansi.magenta": "#b4bbc8",
        "terminal.ansi.red": "#cc6666",
        "terminal.ansi.white": "#b4b7b4",
        "terminal.ansi.yellow": "#d7bd8d",
        "terminal.background": "#191b1d",
        "terminal.bright_foreground": "#ffffff",
        "terminal.dim_foreground": "#b4b7b4",
        "terminal.foreground": "#c5c8c6",
        "text": "#c5c8c6",
        "text.accent": "#8abdb6",
        "text.disabled": "#616875",
        "text.muted": "#b4b7b4",
        "text.placeholder": "#b4b7b4",
        "title_bar.background": "#191b1d",
        "title_bar.inactive_background": "#191b1d",
        "toolbar.background": "#191b1d",
        "toolbar.hover_background": "#545B68",
        "unreachable": "#cc6666",
        "unreachable.background": "#1d1f21",
        "unreachable.border": "#353b45",
        "version_control.added": "#a4b595",
        "version_control.conflict": "#DE935F",
        "version_control.conflict_marker.ours": "#a4b59533",
        "version_control.conflict_marker.theirs": "#6f8dab33",
        "version_control.deleted": "#cc6666",
        "version_control.ignored": "#676e7b",
        "version_control.modified": "#6f8dab",
        "version_control.renamed": "#8abdb6",
        "vim.helix_normal.background": "#6f8dab",
        "vim.helix_normal.foreground": "#1d1f21",
        "vim.helix_select.background": "#8abdb6",
        "vim.helix_select.foreground": "#1d1f21",
        "vim.insert.background": "#a4b595",
        "vim.insert.foreground": "#1d1f21",
        "vim.mode.text": "#c5c8c6",
        "vim.normal.background": "#6f8dab",
        "vim.normal.foreground": "#1d1f21",
        "vim.replace.background": "#cc6666",
        "vim.replace.foreground": "#1d1f21",
        "vim.visual.background": "#b4bbc8",
        "vim.visual.foreground": "#1d1f21",
        "vim.visual_block.background": "#DE935F",
        "vim.visual_block.foreground": "#1d1f21",
        "vim.visual_line.background": "#d7bd8d",
        "vim.visual_line.foreground": "#1d1f21",
        "warning": "#d7bd8d",
        "warning.background": "#1d1f21",
        "warning.border": "#353b45"
      }
    }
  ]
}
