{
  "$schema": "vscode://schemas/color-theme",
  "name": "NvChad Vesper",
  "type": "dark",
  "semanticHighlighting": true,
  "colors": {
    "foreground": "#FFFFFF",
    "disabledForeground": "#7E7E7E",
    "errorForeground": "#FF8080",
    "focusBorder": "#FFC799",
    "contrastBorder": "#545454",
    "contrastActiveBorder": "#FFC799",
    "selection.background": "#FFC7993d",
    "textLink.foreground": "#99FFE4",
    "textLink.activeForeground": "#FFC799",
    "textPreformat.foreground": "#FFCFA8",
    "textBlockQuote.background": "#1C1C1C",
    "textBlockQuote.border": "#373737",
    "textCodeBlock.background": "#1C1C1C",
    "textSeparator.foreground": "#373737",
    "descriptionForeground": "#7E7E7E",
    "icon.foreground": "#FFC799",
    "sash.hoverBorder": "#FFC799",
    "badge.background": "#FFC799",
    "badge.foreground": "#101010",
    "progressBar.background": "#FFC799",
    "titleBar.activeBackground": "#1C1C1C",
    "titleBar.activeForeground": "#FFFFFF",
    "titleBar.inactiveBackground": "#1C1C1C",
    "titleBar.inactiveForeground": "#7E7E7E",
    "activityBar.background": "#0a0a0a",
    "activityBar.foreground": "#FFFFFF",
    "activityBar.inactiveForeground": "#7E7E7E",
    "activityBar.activeBorder": "#FFC799",
    "activityBarBadge.background": "#99FFE4",
    "activityBarBadge.foreground": "#101010",
    "sideBar.background": "#0a0a0a",
    "sideBar.foreground": "#FFFFFF",
    "sideBar.border": "#545454",
    "sideBarTitle.foreground": "#FFFFFF",
    "sideBarSectionHeader.background": "#1C1C1C",
    "sideBarSectionHeader.foreground": "#FFFFFF",
    "sideBarSectionHeader.border": "#373737",
    "list.activeSelectionBackground": "#FFC79959",
    "list.activeSelectionForeground": "#FFFFFF",
    "list.inactiveSelectionBackground": "#343434d6",
    "list.inactiveSelectionForeground": "#FFFFFF",
    "list.hoverBackground": "#282828b8",
    "list.hoverForeground": "#FFFFFF",
    "list.focusBackground": "#FFC79966",
    "list.focusForeground": "#FFFFFF",
    "list.highlightForeground": "#99FFE4",
    "list.errorForeground": "#FF8080",
    "list.warningForeground": "#FFC799",
    "tree.indentGuidesStroke": "#505050",
    "editorGroupHeader.tabsBackground": "#1C1C1C",
    "editorGroupHeader.tabsBorder": "#545454",
    "tab.border": "#545454",
    "tab.activeBackground": "#101010",
    "tab.activeForeground": "#FFFFFF",
    "tab.activeBorderTop": "#FFC799",
    "tab.inactiveBackground": "#1C1C1C",
    "tab.inactiveForeground": "#7E7E7E",
    "tab.inactiveModifiedBorder": "#FFC799",
    "tab.unfocusedActiveBorderTop": "#FFC7998c",
    "tab.unfocusedInactiveForeground": "#6e6e6e",
    "editor.background": "#101010",
    "editor.foreground": "#FFFFFF",
    "editorLineNumber.foreground": "#595959",
    "editorLineNumber.activeForeground": "#FFC799",
    "editorCursor.foreground": "#FFFFFF",
    "editorCursor.background": "#101010",
    "editor.selectionBackground": "#FFC79959",
    "editor.selectionHighlightBackground": "#99FFE424",
    "editor.inactiveSelectionBackground": "#343434b8",
    "editor.wordHighlightBackground": "#FFC79924",
    "editor.wordHighlightStrongBackground": "#FFC7992e",
    "editor.findMatchBackground": "#99FFE452",
    "editor.findMatchBorder": "#99FFE4",
    "editor.findMatchHighlightBackground": "#99FFE424",
    "editor.findRangeHighlightBackground": "#3434348c",
    "editor.hoverHighlightBackground": "#28282873",
    "editor.lineHighlightBackground": "#1C1C1C",
    "editor.lineHighlightBorder": "#FFFFFF0d",
    "editorLink.activeForeground": "#99FFE4",
    "editorWhitespace.foreground": "#505050a6",
    "editorIndentGuide.background1": "#505050",
    "editorIndentGuide.activeBackground1": "#595959",
    "editorRuler.foreground": "#3b3b3b",
    "editorBracketMatch.background": "#343434d9",
    "editorBracketMatch.border": "#99FFE4",
    "editorBracketHighlight.foreground1": "#FFC799",
    "editorBracketHighlight.foreground2": "#99FFE4",
    "editorBracketHighlight.foreground3": "#FFC799",
    "editorBracketHighlight.foreground4": "#FBADFF",
    "editorBracketHighlight.foreground5": "#FFC799",
    "editorBracketHighlight.foreground6": "#99FFE4",
    "editorBracketPairGuide.background1": "#FFC79942",
    "editorBracketPairGuide.background2": "#99FFE442",
    "editorBracketPairGuide.background3": "#FFC79942",
    "editorBracketPairGuide.background4": "#FBADFF42",
    "editorBracketPairGuide.background5": "#FFC79942",
    "editorBracketPairGuide.background6": "#99FFE442",
    "editorBracketPairGuide.activeBackground1": "#FFC799",
    "editorBracketPairGuide.activeBackground2": "#99FFE4",
    "editorBracketPairGuide.activeBackground3": "#FFC799",
    "editorBracketPairGuide.activeBackground4": "#FBADFF",
    "editorBracketPairGuide.activeBackground5": "#FFC799",
    "editorBracketPairGuide.activeBackground6": "#99FFE4",
    "editorGutter.background": "#101010",
    "editorGutter.modifiedBackground": "#FFC799",
    "editorGutter.addedBackground": "#99FFE4",
    "editorGutter.deletedBackground": "#FF8080",
    "editorError.foreground": "#FF8080",
    "editorWarning.foreground": "#FFC799",
    "editorInfo.foreground": "#99FFE4",
    "editorHint.foreground": "#FBADFF",
    "editorOverviewRuler.errorForeground": "#FF8080cc",
    "editorOverviewRuler.warningForeground": "#FFC799cc",
    "editorOverviewRuler.infoForeground": "#99FFE4cc",
    "editorOverviewRuler.bracketMatchForeground": "#99FFE4cc",
    "editorOverviewRuler.modifiedForeground": "#FFC799cc",
    "editorOverviewRuler.addedForeground": "#99FFE4cc",
    "editorOverviewRuler.deletedForeground": "#FF8080cc",
    "editorWidget.background": "#1C1C1C",
    "editorWidget.foreground": "#FFFFFF",
    "editorWidget.border": "#414141",
    "editorSuggestWidget.background": "#1C1C1C",
    "editorSuggestWidget.border": "#414141",
    "editorSuggestWidget.foreground": "#FFFFFF",
    "editorSuggestWidget.highlightForeground": "#99FFE4",
    "editorSuggestWidget.selectedBackground": "#FFC79959",
    "editorHoverWidget.background": "#1C1C1C",
    "editorHoverWidget.foreground": "#FFFFFF",
    "editorHoverWidget.border": "#414141",
    "editorMarkerNavigation.background": "#1C1C1C",
    "peekView.border": "#414141",
    "peekViewEditor.background": "#101010",
    "peekViewEditor.matchHighlightBackground": "#99FFE438",
    "peekViewResult.background": "#1C1C1C",
    "peekViewResult.selectionBackground": "#FFC79959",
    "peekViewResult.matchHighlightBackground": "#99FFE429",
    "peekViewTitle.background": "#1C1C1C",
    "peekViewTitleLabel.foreground": "#FFFFFF",
    "peekViewTitleDescription.foreground": "#7E7E7E",
    "panel.background": "#1C1C1C",
    "panel.border": "#545454",
    "panelTitle.activeBorder": "#FFC799",
    "panelTitle.activeForeground": "#FFFFFF",
    "panelTitle.inactiveForeground": "#7E7E7E",
    "statusBar.background": "#1C1C1C",
    "statusBar.foreground": "#FFFFFF",
    "statusBar.border": "#545454",
    "statusBar.debuggingBackground": "#FFC799",
    "statusBar.debuggingForeground": "#101010",
    "statusBar.noFolderBackground": "#1C1C1C",
    "statusBarItem.hoverBackground": "#343434e6",
    "statusBarItem.prominentBackground": "#282828e6",
    "statusBarItem.remoteBackground": "#FFC799",
    "statusBarItem.remoteForeground": "#101010",
    "terminal.background": "#101010",
    "terminal.foreground": "#FFFFFF",
    "terminal.selectionBackground": "#FFC79959",
    "terminal.border": "#414141",
    "terminalCursor.foreground": "#FFFFFF",
    "terminalCursor.background": "#101010",
    "terminal.ansiBlack": "#1C1C1C",
    "terminal.ansiRed": "#FF8080",
    "terminal.ansiGreen": "#99FFE4",
    "terminal.ansiYellow": "#FFC799",
    "terminal.ansiBlue": "#FFC799",
    "terminal.ansiMagenta": "#FBADFF",
    "terminal.ansiCyan": "#99FFE4",
    "terminal.ansiWhite": "#FFFFFF",
    "terminal.ansiBrightBlack": "#595959",
    "terminal.ansiBrightRed": "#FFC799",
    "terminal.ansiBrightGreen": "#99FFE4",
    "terminal.ansiBrightYellow": "#FFCFA8",
    "terminal.ansiBrightBlue": "#FFC799",
    "terminal.ansiBrightMagenta": "#FBADFF",
    "terminal.ansiBrightCyan": "#99FFE4",
    "terminal.ansiBrightWhite": "#FFFFFF",
    "input.background": "#1C1C1C",
    "input.foreground": "#FFFFFF",
    "input.border": "#414141",
    "input.placeholderForeground": "#7E7E7E",
    "inputOption.activeBorder": "#FFC799",
    "inputValidation.errorBackground": "#FF80801a",
    "inputValidation.errorBorder": "#FF8080",
    "inputValidation.warningBackground": "#FFC7991a",
    "inputValidation.warningBorder": "#FFC799",
    "inputValidation.infoBackground": "#FFC7991a",
    "inputValidation.infoBorder": "#FFC799",
    "dropdown.background": "#1C1C1C",
    "dropdown.foreground": "#FFFFFF",
    "dropdown.border": "#414141",
    "checkbox.background": "#1C1C1C",
    "checkbox.border": "#414141",
    "checkbox.foreground": "#FFFFFF",
    "button.background": "#FFC799",
    "button.foreground": "#101010",
    "button.hoverBackground": "#FFC799",
    "button.secondaryBackground": "#282828",
    "button.secondaryForeground": "#FFFFFF",
    "button.secondaryHoverBackground": "#343434",
    "quickInput.background": "#1C1C1C",
    "quickInput.foreground": "#FFFFFF",
    "quickInputList.focusBackground": "#FFC79959",
    "pickerGroup.border": "#414141",
    "pickerGroup.foreground": "#99FFE4",
    "menu.background": "#1C1C1C",
    "menu.foreground": "#FFFFFF",
    "menu.selectionBackground": "#FFC79959",
    "menu.selectionForeground": "#FFFFFF",
    "menu.border": "#414141",
    "notificationCenterHeader.background": "#1C1C1C",
    "notificationCenterHeader.foreground": "#FFFFFF",
    "notifications.background": "#1C1C1C",
    "notifications.foreground": "#FFFFFF",
    "notifications.border": "#414141",
    "scrollbar.shadow": "#10101073",
    "scrollbarSlider.background": "#343434a6",
    "scrollbarSlider.hoverBackground": "#505050b3",
    "scrollbarSlider.activeBackground": "#6e6e6ed1",
    "breadcrumb.background": "#101010",
    "breadcrumb.foreground": "#7E7E7E",
    "breadcrumb.activeSelectionForeground": "#FFFFFF",
    "breadcrumb.focusForeground": "#99FFE4",
    "commandCenter.background": "#282828b3",
    "commandCenter.foreground": "#FFFFFF",
    "commandCenter.border": "#414141",
    "minimap.background": "#101010",
    "minimap.selectionHighlight": "#FFC79959",
    "minimap.findMatchHighlight": "#99FFE44d",
    "minimap.errorHighlight": "#FF808073",
    "minimap.warningHighlight": "#FFC79973",
    "minimapGutter.addedBackground": "#99FFE4",
    "minimapGutter.modifiedBackground": "#FFC799",
    "minimapGutter.deletedBackground": "#FF8080",
    "gitDecoration.addedResourceForeground": "#99FFE4",
    "gitDecoration.modifiedResourceForeground": "#FFC799",
    "gitDecoration.deletedResourceForeground": "#FF8080",
    "gitDecoration.renamedResourceForeground": "#99FFE4",
    "gitDecoration.untrackedResourceForeground": "#99FFE4",
    "gitDecoration.ignoredResourceForeground": "#7E7E7E",
    "diffEditor.insertedTextBackground": "#1e2825ff",
    "diffEditor.removedTextBackground": "#281b1bff",
    "diffEditor.insertedLineBackground": "#99FFE414",
    "diffEditor.removedLineBackground": "#FF808014",
    "diffEditor.diagonalFill": "#414141",
    "diffEditor.border": "#545454",
    "diffEditorOverview.insertedForeground": "#99FFE4cc",
    "diffEditorOverview.removedForeground": "#FF8080cc",
    "merge.currentHeaderBackground": "#FFC79933",
    "merge.currentContentBackground": "#FFC79914",
    "merge.incomingHeaderBackground": "#99FFE433",
    "merge.incomingContentBackground": "#99FFE414",
    "merge.border": "#414141",
    "merge.commonContentBackground": "#34343459",
    "merge.commonHeaderBackground": "#50505059",
    "problemsErrorIcon.foreground": "#FF8080",
    "problemsWarningIcon.foreground": "#FFC799",
    "problemsInfoIcon.foreground": "#99FFE4",
    "debugIcon.breakpointForeground": "#FF8080",
    "debugIcon.breakpointDisabledForeground": "#7E7E7E",
    "debugIcon.startForeground": "#99FFE4",
    "debugIcon.pauseForeground": "#FFC799",
    "debugIcon.stopForeground": "#FF8080",
    "debugTokenExpression.string": "#99FFE4",
    "debugTokenExpression.number": "#FFC799",
    "debugTokenExpression.boolean": "#FFC799",
    "debugTokenExpression.name": "#FFC799",
    "settings.headerForeground": "#FFFFFF",
    "settings.modifiedItemIndicator": "#99FFE4",
    "settings.dropdownBackground": "#1C1C1C",
    "settings.dropdownForeground": "#FFFFFF",
    "settings.dropdownBorder": "#414141",
    "settings.numberInputBackground": "#1C1C1C",
    "settings.numberInputForeground": "#FFFFFF",
    "settings.numberInputBorder": "#414141",
    "settings.textInputBackground": "#1C1C1C",
    "settings.textInputForeground": "#FFFFFF",
    "settings.textInputBorder": "#414141",
    "chat.background": "#232323",
    "chat.foreground": "#FFFFFF",
    "chat.border": "#414141",
    "chat.slashCommandBackground": "#282828e6",
    "chat.slashCommandForeground": "#99FFE4",
    "chat.requestBackground": "#1C1C1C",
    "chat.requestBorder": "#414141",
    "chat.responseBackground": "#232323",
    "inlineChat.background": "#1C1C1C",
    "inlineChat.border": "#414141",
    "inlineChat.foreground": "#FFFFFF",
    "inlineChatInput.border": "#414141",
    "inlineChatInput.focusBorder": "#FFC799",
    "profileBadge.background": "#FFC799",
    "profileBadge.foreground": "#101010",
    "welcomePage.tileBackground": "#232323",
    "welcomePage.tileHoverBackground": "#282828",
    "welcomePage.progress.background": "#343434",
    "welcomePage.progress.foreground": "#FFC799",
    "ports.iconRunningProcessForeground": "#99FFE4",
    "editorGroup.border": "#282828",
    "widget.shadow": "#10101073",
    "editorInlayHint.background": "#1C1C1Ce6",
    "editorInlayHint.foreground": "#7E7E7E",
    "editorInlayHint.typeForeground": "#FBADFF",
    "editorInlayHint.parameterForeground": "#FFC799",
    "testing.iconFailed": "#FF8080",
    "testing.iconErrored": "#FF8080",
    "testing.iconPassed": "#99FFE4",
    "testing.iconQueued": "#FFC799",
    "testing.iconSkipped": "#7E7E7E",
    "testing.iconUnset": "#595959",
    "testing.peekBorder": "#282828",
    "testing.message.error.decorationForeground": "#FF8080",
    "testing.message.info.decorationForeground": "#FFC799",
    "testing.runAction": "#99FFE4",
    "symbolIcon.folderForeground": "#FFC799",
    "symbolIcon.classForeground": "#FBADFF",
    "symbolIcon.functionForeground": "#FFC799",
    "symbolIcon.variableForeground": "#FFFFFF",
    "symbolIcon.methodForeground": "#FFC799",
    "symbolIcon.propertyForeground": "#FFC799",
    "symbolIcon.interfaceForeground": "#FBADFF",
    "symbolIcon.enumForeground": "#FBADFF",
    "symbolIcon.constantForeground": "#FFC799",
    "symbolIcon.namespaceForeground": "#FFC799",
    "symbolIcon.moduleForeground": "#FFC799",
    "symbolIcon.structForeground": "#FBADFF"
  },
  "tokenColors": [
    {
      "name": "variable (variable)",
      "scope": "variable",
      "settings": {
        "foreground": "#FFFFFF"
      }
    },
    {
      "name": "variable (meta.definition.variable)",
      "scope": "meta.definition.variable",
      "settings": {
        "foreground": "#FFFFFF"
      }
    },
    {
      "name": "variable (support.variable)",
      "scope": "support.variable",
      "settings": {
        "foreground": "#FFFFFF"
      }
    },
    {
      "name": "variable.builtin (variable.language)",
      "scope": "variable.language",
      "settings": {
        "foreground": "#FFC799"
      }
    },
    {
      "name": "variable.parameter (variable.parameter)",
      "scope": "variable.parameter",
      "settings": {
        "foreground": "#FFC799"
      }
    },
    {
      "name": "variable.parameter (meta.parameter)",
      "scope": "meta.parameter",
      "settings": {
        "foreground": "#FFC799"
      }
    },
    {
      "name": "variable.member (variable.other.property)",
      "scope": "variable.other.property",
      "settings": {
        "foreground": "#FFC799"
      }
    },
    {
      "name": "variable.member (variable.other.member)",
      "scope": "variable.other.member",
      "settings": {
        "foreground": "#FFC799"
      }
    },
    {
      "name": "variable.member.key (meta.object-literal.key)",
      "scope": "meta.object-literal.key",
      "settings": {
        "foreground": "#FFC799"
      }
    },
    {
      "name": "module (entity.name.namespace)",
      "scope": "entity.name.namespace",
      "settings": {
        "foreground": "#FFC799"
      }
    },
    {
      "name": "module (support.module)",
      "scope": "support.module",
      "settings": {
        "foreground": "#FFC799"
      }
    },
    {
      "name": "constant (constant)",
      "scope": "constant",
      "settings": {
        "foreground": "#FFC799"
      }
    },
    {
      "name": "constant (constant.other)",
      "scope": "constant.other",
      "settings": {
        "foreground": "#FFC799"
      }
    },
    {
      "name": "constant (support.constant)",
      "scope": "support.constant",
      "settings": {
        "foreground": "#FFC799"
      }
    },
    {
      "name": "constant.builtin (constant.language)",
      "scope": "constant.language",
      "settings": {
        "foreground": "#FFC799"
      }
    },
    {
      "name": "constant.builtin (support.constant)",
      "scope": "support.constant",
      "settings": {
        "foreground": "#FFC799"
      }
    },
    {
      "name": "constant.macro (entity.name.function.preprocessor)",
      "scope": "entity.name.function.preprocessor",
      "settings": {
        "foreground": "#FFC799"
      }
    },
    {
      "name": "string (string)",
      "scope": "string",
      "settings": {
        "foreground": "#99FFE4"
      }
    },
    {
      "name": "string (string.quoted)",
      "scope": "string.quoted",
      "settings": {
        "foreground": "#99FFE4"
      }
    },
    {
      "name": "string (string.template)",
      "scope": "string.template",
      "settings": {
        "foreground": "#99FFE4"
      }
    },
    {
      "name": "string (string.interpolated)",
      "scope": "string.interpolated",
      "settings": {
        "foreground": "#99FFE4"
      }
    },
    {
      "name": "string.regex (string.regexp)",
      "scope": "string.regexp",
      "settings": {
        "foreground": "#838383"
      }
    },
    {
      "name": "string.regex (constant.other.character-class.regexp)",
      "scope": "constant.other.character-class.regexp",
      "settings": {
        "foreground": "#838383"
      }
    },
    {
      "name": "string.escape (constant.character.escape)",
      "scope": "constant.character.escape",
      "settings": {
        "foreground": "#838383"
      }
    },
    {
      "name": "character (constant.character)",
      "scope": "constant.character",
      "settings": {
        "foreground": "#FFC799"
      }
    },
    {
      "name": "number (constant.numeric)",
      "scope": "constant.numeric",
      "settings": {
        "foreground": "#FFC799"
      }
    },
    {
      "name": "number (constant.language.boolean)",
      "scope": "constant.language.boolean",
      "settings": {
        "foreground": "#FFC799"
      }
    },
    {
      "name": "number (constant.language.null)",
      "scope": "constant.language.null",
      "settings": {
        "foreground": "#FFC799"
      }
    },
    {
      "name": "number.float (constant.numeric.float)",
      "scope": "constant.numeric.float",
      "settings": {
        "foreground": "#FFC799"
      }
    },
    {
      "name": "annotation (storage.type.annotation)",
      "scope": "storage.type.annotation",
      "settings": {
        "foreground": "#FF8080"
      }
    },
    {
      "name": "attribute (entity.other.attribute-name)",
      "scope": "entity.other.attribute-name",
      "settings": {
        "foreground": "#FBADFF"
      }
    },
    {
      "name": "keyword.exception (keyword.control.exception)",
      "scope": "keyword.control.exception",
      "settings": {
        "foreground": "#FFC799"
      }
    },
    {
      "name": "keyword (keyword)",
      "scope": "keyword",
      "settings": {
        "foreground": "#FBADFF"
      }
    },
    {
      "name": "keyword (keyword.control)",
      "scope": "keyword.control",
      "settings": {
        "foreground": "#FBADFF"
      }
    },
    {
      "name": "keyword (storage)",
      "scope": "storage",
      "settings": {
        "foreground": "#FBADFF"
      }
    },
    {
      "name": "keyword (storage.modifier)",
      "scope": "storage.modifier",
      "settings": {
        "foreground": "#FBADFF"
      }
    },
    {
      "name": "keyword.function (keyword.other.function)",
      "scope": "keyword.other.function",
      "settings": {
        "foreground": "#FBADFF"
      }
    },
    {
      "name": "keyword.return (keyword.control.flow)",
      "scope": "keyword.control.flow",
      "settings": {
        "foreground": "#FBADFF"
      }
    },
    {
      "name": "keyword.operator (keyword.operator)",
      "scope": "keyword.operator",
      "settings": {
        "foreground": "#FBADFF"
      }
    },
    {
      "name": "keyword.import (keyword.control.import)",
      "scope": "keyword.control.import",
      "settings": {
        "foreground": "#FBADFF"
      }
    },
    {
      "name": "keyword.import (keyword.other.import)",
      "scope": "keyword.other.import",
      "settings": {
        "foreground": "#FBADFF"
      }
    },
    {
      "name": "keyword.conditional (keyword.control.conditional)",
      "scope": "keyword.control.conditional",
      "settings": {
        "foreground": "#FBADFF"
      }
    },
    {
      "name": "keyword.repeat (keyword.control.loop)",
      "scope": "keyword.control.loop",
      "settings": {
        "foreground": "#FBADFF"
      }
    },
    {
      "name": "keyword.storage (storage.type)",
      "scope": "storage.type",
      "settings": {
        "foreground": "#FBADFF"
      }
    },
    {
      "name": "keyword.directive (keyword.other.important)",
      "scope": "keyword.other.important",
      "settings": {
        "foreground": "#FBADFF"
      }
    },
    {
      "name": "function (entity.name.function)",
      "scope": "entity.name.function",
      "settings": {
        "foreground": "#FFC799",
        "fontStyle": "italic"
      }
    },
    {
      "name": "function (support.function)",
      "scope": "support.function",
      "settings": {
        "foreground": "#FFC799",
        "fontStyle": "italic"
      }
    },
    {
      "name": "function (meta.function-call)",
      "scope": "meta.function-call",
      "settings": {
        "foreground": "#FFC799",
        "fontStyle": "italic"
      }
    },
    {
      "name": "function.builtin (support.function)",
      "scope": "support.function",
      "settings": {
        "foreground": "#FFC799"
      }
    },
    {
      "name": "function.macro (entity.name.function.preprocessor)",
      "scope": "entity.name.function.preprocessor",
      "settings": {
        "foreground": "#FFC799"
      }
    },
    {
      "name": "function.call (meta.function-call)",
      "scope": "meta.function-call",
      "settings": {
        "foreground": "#FFC799"
      }
    },
    {
      "name": "function.method (entity.name.method)",
      "scope": "entity.name.method",
      "settings": {
        "foreground": "#FFC799"
      }
    },
    {
      "name": "function.method (meta.method-call)",
      "scope": "meta.method-call",
      "settings": {
        "foreground": "#FFC799"
      }
    },
    {
      "name": "function.method.call (meta.method-call)",
      "scope": "meta.method-call",
      "settings": {
        "foreground": "#FFC799"
      }
    },
    {
      "name": "constructor (meta.function-call.constructor)",
      "scope": "meta.function-call.constructor",
      "settings": {
        "foreground": "#838383"
      }
    },
    {
      "name": "constructor (support.class)",
      "scope": "support.class",
      "settings": {
        "foreground": "#838383"
      }
    },
    {
      "name": "operator (keyword.operator)",
      "scope": "keyword.operator",
      "settings": {
        "foreground": "#FFFFFF"
      }
    },
    {
      "name": "operator (punctuation.accessor)",
      "scope": "punctuation.accessor",
      "settings": {
        "foreground": "#FFFFFF"
      }
    },
    {
      "name": "punctuation.bracket (punctuation.section.brackets)",
      "scope": "punctuation.section.brackets",
      "settings": {
        "foreground": "#FFC799"
      }
    },
    {
      "name": "punctuation.bracket (punctuation.definition.brackets)",
      "scope": "punctuation.definition.brackets",
      "settings": {
        "foreground": "#FFC799"
      }
    },
    {
      "name": "punctuation.delimiter (punctuation.separator)",
      "scope": "punctuation.separator",
      "settings": {
        "foreground": "#FFFFFF"
      }
    },
    {
      "name": "punctuation.delimiter (punctuation.terminator)",
      "scope": "punctuation.terminator",
      "settings": {
        "foreground": "#FFFFFF"
      }
    },
    {
      "name": "symbol (constant.other.symbol)",
      "scope": "constant.other.symbol",
      "settings": {
        "foreground": "#99FFE4"
      }
    },
    {
      "name": "tag (entity.name.tag)",
      "scope": "entity.name.tag",
      "settings": {
        "foreground": "#FBADFF"
      }
    },
    {
      "name": "tag.attribute (entity.other.attribute-name)",
      "scope": "entity.other.attribute-name",
      "settings": {
        "foreground": "#FFC799"
      }
    },
    {
      "name": "tag.delimiter (punctuation.definition.tag)",
      "scope": "punctuation.definition.tag",
      "settings": {
        "foreground": "#FFC799"
      }
    },
    {
      "name": "text (string.quoted.other)",
      "scope": "string.quoted.other",
      "settings": {
        "foreground": "#FFFFFF"
      }
    },
    {
      "name": "text.emphasis (markup.italic)",
      "scope": "markup.italic",
      "settings": {
        "foreground": "#FFC799"
      }
    },
    {
      "name": "type.builtin (storage.type)",
      "scope": "storage.type",
      "settings": {
        "foreground": "#FBADFF"
      }
    },
    {
      "name": "type.builtin (support.type)",
      "scope": "support.type",
      "settings": {
        "foreground": "#FBADFF"
      }
    },
    {
      "name": "type.builtin (entity.name.type)",
      "scope": "entity.name.type",
      "settings": {
        "foreground": "#FBADFF"
      }
    },
    {
      "name": "type.builtin (entity.name.class)",
      "scope": "entity.name.class",
      "settings": {
        "foreground": "#FBADFF"
      }
    },
    {
      "name": "property (variable.other.property)",
      "scope": "variable.other.property",
      "settings": {
        "foreground": "#FFC799"
      }
    },
    {
      "name": "property (support.type.property-name)",
      "scope": "support.type.property-name",
      "settings": {
        "foreground": "#FFC799"
      }
    },
    {
      "name": "property (entity.other.attribute-name)",
      "scope": "entity.other.attribute-name",
      "settings": {
        "foreground": "#FFC799"
      }
    },
    {
      "name": "markup.heading (markup.heading)",
      "scope": "markup.heading",
      "settings": {
        "foreground": "#FFC799",
        "fontStyle": "bold"
      }
    },
    {
      "name": "markup.heading (entity.name.section)",
      "scope": "entity.name.section",
      "settings": {
        "foreground": "#FFC799",
        "fontStyle": "bold"
      }
    },
    {
      "name": "markup.link (markup.underline.link)",
      "scope": "markup.underline.link",
      "settings": {
        "foreground": "#FFC799"
      }
    },
    {
      "name": "markup.link (string.other.link)",
      "scope": "string.other.link",
      "settings": {
        "foreground": "#FFC799"
      }
    },
    {
      "name": "markup.link.url (markup.underline.link)",
      "scope": "markup.underline.link",
      "settings": {
        "foreground": "#FFC799",
        "fontStyle": "underline"
      }
    },
    {
      "name": "markup.italic (markup.italic)",
      "scope": "markup.italic",
      "settings": {
        "foreground": "#FFFFFF",
        "fontStyle": "italic"
      }
    },
    {
      "name": "markup.strong (markup.bold)",
      "scope": "markup.bold",
      "settings": {
        "foreground": "#FFC799",
        "fontStyle": "bold"
      }
    },
    {
      "name": "comment (comment)",
      "scope": "comment",
      "settings": {
        "foreground": "#595959",
        "fontStyle": "italic"
      }
    },
    {
      "name": "comment (punctuation.definition.comment)",
      "scope": "punctuation.definition.comment",
      "settings": {
        "foreground": "#595959",
        "fontStyle": "italic"
      }
    },
    {
      "name": "comment.doc (comment.block.documentation)",
      "scope": "comment.block.documentation",
      "settings": {
        "foreground": "#6e6e6e",
        "fontStyle": "italic"
      }
    },
    {
      "name": "comment.doc (string.quoted.doc)",
      "scope": "string.quoted.doc",
      "settings": {
        "foreground": "#6e6e6e",
        "fontStyle": "italic"
      }
    },
    {
      "name": "Number (constant.numeric)",
      "scope": "constant.numeric",
      "settings": {
        "foreground": "#FFC799"
      }
    },
    {
      "name": "Number (constant.language.boolean)",
      "scope": "constant.language.boolean",
      "settings": {
        "foreground": "#FFC799"
      }
    }
  ],
  "semanticTokenColors": {
    "variable": "#FFFFFF",
    "parameter": "#FFC799",
    "namespace": "#FFC799",
    "number": "#FFC799",
    "string": "#99FFE4",
    "regexp": "#838383",
    "keyword": "#FBADFF",
    "function": {
      "foreground": "#FFC799",
      "italic": true
    },
    "method": "#FFC799",
    "type": "#FBADFF",
    "property": "#FFC799",
    "comment": {
      "foreground": "#595959",
      "italic": true
    },
    "typeParameter": "#FBADFF",
    "class": "#FBADFF",
    "interface": "#FBADFF",
    "enum": "#FBADFF",
    "enumMember": "#FFC799",
    "struct": "#FBADFF",
    "decorator": "#FFC799",
    "macro": "#FFC799",
    "label": "#FBADFF",
    "event": "#FFC799",
    "modifier": "#FFC799",
    "operator": "#FFFFFF",
    "variable.defaultLibrary": "#FFC799",
    "variable.readonly.defaultLibrary": "#FFC799",
    "type.defaultLibrary": "#FBADFF",
    "variable.readonly": "#FFFFFF",
    "selfKeyword": "#FBADFF"
  }
}
